pyeasypm/.DS_Store
pyeasypm/__init__.py
pyeasypm/main.py
pyeasypm-0.1.0.dist-info/METADATA
pyeasypm-0.1.0.dist-info/WHEEL
pyeasypm-0.1.0.dist-info/entry_points.txt
pyeasypm-0.1.0.dist-info/RECORD
