Metadata-Version: 2.1
Name: pyeasypm
Version: 0.1.0
Summary: An easy project package manager for python
Author: Kushagra Singh Visen
Author-email: kushagrasingh025@gmail.com
Requires-Python: >=3.12,<4.0
Classifier: Programming Language :: Python :: 3
Classifier: Programming Language :: Python :: 3.12
Requires-Dist: typer[all] (>=0.12.3,<0.13.0)
